birddata/__init__.py
birddata/bird_dataset.csv
birddata/loader.py
birddata-0.1.1.dist-info/METADATA
birddata-0.1.1.dist-info/WHEEL
birddata-0.1.1.dist-info/top_level.txt
birddata-0.1.1.dist-info/RECORD
