Metadata-Version: 2.1
Name: birddata
Version: 0.1.1
Summary: A beginner-friendly bird classification dataset
Author: Pratiksha Rawat
Author-email: your@email.com
Classifier: Programming Language :: Python :: 3
Classifier: License :: OSI Approved :: MIT License
Requires-Python: >=3.6
